Workbook

Sheet Proyecciones
B1: Año 1 | C1: Año 2 | D1: Año 3
A2: Costos fijos | B2: =Estimaciones!C4 | C2: =Estimaciones!D4 | D2: =Estimaciones!E4
A3: Costos variables | B3: =Estimaciones!C11 | C3: =Estimaciones!D11 | D3: =Estimaciones!E11
A7: Proyecciones | B7: Año 1 | N7: Año 2 | Z7: Año 3
B8: M1 | C8: M2 | D8: M3 | E8: M4 | F8: M5 | G8: M6 | H8: M7 | I8: M8 | J8: M9 | K8: M10 | L8: M11 | M8: M12 | N8: M1 | O8: M2 | P8: M3 | Q8: M4 | R8: M5 | S8: M6 | T8: M7 | U8: M8 | V8: M9 | W8: M10 | X8: M11 | Y8: M12 | Z8: M1 | AA8: M2 | AB8: M3 | AC8: M4 | AD8: M5 | AE8: M6 | AF8: M7 | AG8: M8 | AH8: M9 | AI8: M10 | AJ8: M11 | AK8: M12
A9: No. de usuarios | B9: 5 | C9: =B9+30 | D9: =C9+30 | E9: =D9+30 | F9: =E9+30 | G9: =F9+30 | H9: =G9+30 | I9: =H9+30 | J9: =I9+30 | ... M9: =L9+30 | N9: =M9+120 | O9: =N9+120 | P9: =O9+120 | Q9: =P9+120 | R9: =Q9+120 | S9: =R9+120 | T9: =S9+120 | U9: =T9+120 | ... Y9: =X9+120 | Z9: =Y9+200 | AA9: =Z9+200 | AB9: =AA9+200 | AC9: =AB9+200 | AD9: =AC9+200 | AE9: =AD9+200 | AF9: =AE9+200 | AG9: =AF9+200 | ... AK9: =AJ9+200
A10: Costos totales | B10: =$B$2+($B$3*B9) | C10: =$B$2+($B$3*C9) | D10: =$B$2+$B$3*D9 | E10: =$B$2+$B$3*E9 | F10: =$B$2+$B$3*F9 | G10: =$B$2+$B$3*G9 | H10: =$B$2+$B$3*H9 | I10: =$B$2+$B$3*I9 | J10: =$B$2+$B$3*J9 | K10: =$B$2+$B$3*K9 | ... M10: =$B$2+$B$3*M9 | N10: =$C$2+$C$3*N9 | O10: =$C$2+$C$3*O9 | P10: =$C$2+$C$3*P9 | Q10: =$C$2+$C$3*Q9 | R10: =$C$2+$C$3*R9 | S10: =$C$2+$C$3*S9 | T10: =$C$2+$C$3*T9 | U10: =$C$2+$C$3*U9 | ... Y10: =$C$2+$C$3*Y9 | Z10: =$D$2+$D$3*Z9 | AA10: =$D$2+$D$3*AA9 | AB10: =$D$2+$D$3*AB9 | AC10: =$D$2+$D$3*AC9 | AD10: =$D$2+$D$3*AD9 | AE10: =$D$2+$D$3*AE9 | AF10: =$D$2+$D$3*AF9 | AG10: =$D$2+$D$3*AG9 | ... AK10: =$D$2+$D$3*AK9
A11: Precio de venta | B11: =Estimaciones!C20 | C11: =$B$11 | D11: =$B$11 | E11: =$B$11 | F11: =$B$11 | G11: =$B$11 | H11: =$B$11 | I11: =$B$11 | J11: =$B$11 | ... M11: =$B$11 | N11: =Estimaciones!D20 | O11: =$N$11 | P11: =$N$11 | Q11: =$N$11 | R11: =$N$11 | S11: =$N$11 | T11: =$N$11 | U11: =$N$11 | V11: =$N$11 | ... Y11: =$N$11 | Z11: =Estimaciones!E20 | AA11: =$Z$11 | AB11: =$Z$11 | AC11: =$Z$11 | AD11: =$Z$11 | AE11: =$Z$11 | AF11: =$Z$11 | AG11: =$Z$11 | AH11: =$Z$11 | ... AK11: =$Z$11
A12: Ingresos totales | B12: =B11*B9 | C12: =C11*C9 | D12: =D11*D9 | E12: =E11*E9 | F12: =F11*F9 | G12: =G11*G9 | H12: =H11*H9 | I12: =I11*I9 | ... AK12: =AK11*AK9
A13: Utilidad operativa (EBITDA) | B13: =B12-B10 | C13: =C12-C10 | D13: =D12-D10 | E13: =E12-E10 | F13: =F12-F10 | G13: =G12-G10 | H13: =H12-H10 | I13: =I12-I10 | ... AK13: =AK12-AK10
D14: Punto de equilibrio | E14: =B2/(E11-B3) | M14: =SUM(B13:M13) | Y14: =SUM(N13:Y13) | AK14: =SUM(Z13:AK13)
A15: (-) Depreciaciones (activos intangibles) y amortizaciones (activos intangibles) 2 al 5% | D15: Ingresos totales | E15: =E14*E11 | M15: =SUM(B13:M13)*0.05 | Y15: =SUM(N13:Y13)*0.05 | AK15: =SUM(Z13:AK13)*0.05
A16: (-) Intereses (Gastos financieros) 0 al 3% | D16: Costos totales | E16: =E14*B3+B2 | M16: =M14*0.03 | Y16: =Y14*0.03 | AK16: =AK14*0.03
A17: Utilidad antes de impuestos (EBT) | M17: =M14-M15-M16 | Y17: =Y14-Y15-Y16 | AK17: =AK14-AK15-AK16
A18: (-) Impuestos (Renta 35%) | M18: =M17*0.35 | Y18: =Y17*0.35 | AK18: =AK17*0.35
A19: Utilidad neta | M19: =M17-M18 | Y19: =Y17-Y18 | AK19: =AK17-AK18 | AL19: =AK19/AK14 | AM19: Uilidad neta

Sheet Estimaciones
B2: Detalle de Costos
B3: Concepto | C3: Año 1 | D3: Año 2 | E3: Año 3 | F3: Descripción
B4: Subtotal Costos fijos mensuales | C4: =SUM(C5:C9) | D4: =SUM(D5:D9) | E4: =SUM(E5:E9)
B5: Desarrollador | C5: 7000000 | D5: =C5*1.08 | E5: =D5*1.08 | F5: Aumento del 8% del SMMLV
B6: CEO | C6: 5000000 | D6: =C6*1.08 | E6: =D6*1.08 | F6: Aumento del 8% del SMMLV
B7: CMO | C7: 4000000 | D7: =C7*1.08 | E7: =D7*1.08 | F7: Aumento del 8% del SMMLV
B8: Gastos de administración | C8: 3500000 | D8: =C8*1.5 | E8: =D8*1.5 | F8: Suscripciones de software, contabilidad, dominio, licencias. Aumento del 50% cada año, dado el aumento de clientes.
B9: Gastos de ventas | C9: 2000000 | D9: =(D10*120) | E9: =(E10*200) | F9: Pauta en redes sociales
B10: CAC | C10: =C9/100 | D10: =C10*1.05 | E10: =D10*1.05
B11: Costos variables por usuario | C11: 28000 | D11: =C11*1.05 | E11: =D11*1.05 | F11: Aumento 5% (IPC).
B12: Subtotal Costos variables | C12: =C11*C17 | D12: =D11*D17 | E12: =E11*E17
B13: Subtotal Costos mensuales | C13: =SUM(C4,C12) | D13: =SUM(D4,D12) | E13: =SUM(E4,E12)
B15: Estimación del precio de venta y utilidades
B16: Precio de venta | C16: Año 1 | D16: Año 2 | E16: Año 3 | F16: Observación
B17: No. de clientes promedio mensual | C17: =AVERAGE(Proyecciones!B9:M9) | D17: =AVERAGE(Proyecciones!N9:Y9) | E17: =AVERAGE(Proyecciones!Z9:AK9)
B18: Costo promedio por cliente mensual | C18: =C13/C17 | D18: =D13/D17 | E18: =E13/E17
B19: Por Margen de utilidad (30%) | C19: =C18*1.3 | D19: =C19*1.05 | E19: =D19*1.05 | F19: Aumento 5% según IPC
B20: Por percepción | C20: 210000 | D20: =C20*1.05 | E20: =D20*1.05
B21: Según competencia | C21: 149900 | D21: =C21*1.05 | E21: =D21*1.05
B22: Ingresos mensuales promedio | C22: =C17*C19 | D22: =D17*D19 | E22: =E17*E19
B23: Utilidad operacional promedio mensual | C23: =C22-C13 | D23: =D22-D13 | E23: =E22-E13
B25: Valoración de la empresa
B26: Valoración pre-money | C26: =(C34*0.90)/0.10 | E26: Activos intangibles (prototipo funcional, tracción inicial, sweat equity) y potencial a futuro (oportunidad de mercado).
B27: Inversión inicial | C27: =SUM(C28:C29)
B28: Operación inicial | C28: =SUM(Proyecciones!B10:F10) | E28: Cinco primeros meses que no percibo utilidades
B29: Creación de la empresa | C29: 2500000
B30: Deuda financiera (Pasivo) | C30: =C27-C34-C33
B31: Patrimonio (Equity) | C31: =SUM(C32:C34) | D31: =SUM(D32:D34)
B32: Aportes propios (idea + código) | C32: =C26 | D32: =C32/C31
B33: Aportes propios en efectivo
B34: Aportes en efectivo de socios | C34: 250000000 | D34: =C34/C31 | E34: A cambio del 10% del negocio. Post-money: $2.500M COP (USD $610K)
B35: "Valoración post-money" | C35: =SUM(C32:C34) | E35: Nuevo patrimonio con aportes de inversionistas. Valor de la empresa hoy con la inversión de socios
B36: Valoración en 3 años | C36: =SUM(Proyecciones!Z13:AK13)*5 | E36: EBITDA (5x)
B37: Valorización de la inversión de socios | C37: =C36*D34 | D37: =C37/C34 | E37: La inversión de los socios se valorizará 53 veces en 3 años.
